triclustering/Pattern.py
triclustering/__init__.py
triclustering/association_rules.py
triclustering/frequent_patterns.py
triclustering/generators.py
triclustering/printing_util.py
triclustering/processor.py
triclustering/suffix_forest.py
triclustering/tricluster.py
triclustering/util.py
triclustering-2023.6.3.0.dist-info/METADATA
triclustering-2023.6.3.0.dist-info/WHEEL
triclustering-2023.6.3.0.dist-info/licenses/LICENSE
triclustering-2023.6.3.0.dist-info/RECORD
