Metadata-Version: 2.1
Name: triclustering
Version: 2023.6.3.0
Summary: Triclustering and association rule mining using Suffix Forest and Frequent Closed Itemset Framework based algorithm.
Project-URL: Homepage, https://github.com/damaclab/SuffixForest-Triclusters-Python
Project-URL: Bug Tracker, https://github.com/damaclab/SuffixForest-Triclusters-Python/issues
Author-email: Dhiraj Bag <dhirajbag.db@gmail.com>
License-File: LICENSE
Classifier: License :: OSI Approved :: MIT License
Classifier: Operating System :: OS Independent
Classifier: Programming Language :: Python :: 3
Requires-Python: >=3.10
Requires-Dist: pandas
Requires-Dist: pydot
